popdyn/__init__.py
popdyn/__version__.py
popdyn/popdyn.py
popdyn-0.6.3.dist-info/LICENSE
popdyn-0.6.3.dist-info/METADATA
popdyn-0.6.3.dist-info/WHEEL
popdyn-0.6.3.dist-info/top_level.txt
popdyn-0.6.3.dist-info/RECORD
