Metadata-Version: 2.1
Name: popdyn
Version: 0.6.3
Summary: Simulation of population dynamics
Home-page: https://github.com/popdynio/popdyn
Author: Popdynio
License: MIT
Platform: UNKNOWN
Classifier: License :: OSI Approved :: MIT License
Classifier: Programming Language :: Python :: 3
Classifier: Programming Language :: Python :: 3.10
Requires-Python: >=3.9
Requires-Dist: gillespy2[sbml]
Requires-Dist: numpy
Requires-Dist: scipy
